setup.py
bin/statsdpy-server
statsdpy/__init__.py
statsdpy/daemonutils.py
statsdpy/statsd.py
statsdpy.egg-info/PKG-INFO
statsdpy.egg-info/SOURCES.txt
statsdpy.egg-info/dependency_links.txt
statsdpy.egg-info/top_level.txt