Metadata-Version: 1.1
Name: statsdpy
Version: 0.0.11
Summary: Eventlet based statsd clone with pickle protocol support
Home-page: http://github.com/pandemicsyn/statsdpy
Author: Florian Hines
Author-email: syn@ronin.io
License: Apache License, (2.0)
Keywords: statsd
Platform: UNKNOWN
Classifier: Development Status :: 4 - Beta
Classifier: License :: OSI Approved :: Apache Software License
Classifier: Operating System :: POSIX :: Linux
Classifier: Programming Language :: Python :: 2.6
Classifier: Environment :: No Input/Output (Daemon)
